{
 "custom_fields": [
  {
   "_assign": null,
   "_comments": null,
   "_liked_by": null,
   "_user_tags": null,
   "allow_in_quick_entry": 0,
   "allow_on_submit": 0,
   "bold": 0,
   "collapsible": 0,
   "collapsible_depends_on": null,
   "columns": 0,
   "creation": "2024-06-20 09:19:57.330016",
   "default": null,
   "depends_on": null,
   "description": null,
   "docstatus": 0,
   "dt": "Efris Settings",
   "fetch_from": null,
   "fetch_if_empty": 0,
   "fieldname": "custom_company",
   "fieldtype": "Link",
   "hidden": 0,
   "hide_border": 0,
   "hide_days": 0,
   "hide_seconds": 0,
   "idx": 11,
   "ignore_user_permissions": 0,
   "ignore_xss_filter": 0,
   "in_global_search": 0,
   "in_list_view": 0,
   "in_preview": 0,
   "in_standard_filter": 0,
   "insert_after": "custom_legal_name",
   "is_system_generated": 0,
   "is_virtual": 0,
   "label": "Company",
   "length": 0,
   "link_filters": null,
   "mandatory_depends_on": null,
   "modified": "2024-06-20 09:19:57.330016",
   "modified_by": "Administrator",
   "module": null,
   "name": "Efris Settings-custom_company",
   "no_copy": 0,
   "non_negative": 0,
   "options": "Company",
   "owner": "Administrator",
   "permlevel": 0,
   "precision": "",
   "print_hide": 0,
   "print_hide_if_no_value": 0,
   "print_width": null,
   "read_only": 0,
   "read_only_depends_on": null,
   "report_hide": 0,
   "reqd": 1,
   "search_index": 0,
   "show_dashboard": 0,
   "sort_options": 0,
   "translatable": 0,
   "unique": 1,
   "width": null
  },
  {
   "_assign": null,
   "_comments": null,
   "_liked_by": null,
   "_user_tags": null,
   "allow_in_quick_entry": 0,
   "allow_on_submit": 0,
   "bold": 0,
   "collapsible": 0,
   "collapsible_depends_on": null,
   "columns": 0,
   "creation": "2024-06-05 18:32:12.040015",
   "default": null,
   "depends_on": null,
   "description": null,
   "docstatus": 0,
   "dt": "Efris Settings",
   "fetch_from": null,
   "fetch_if_empty": 0,
   "fieldname": "custom_place_of_businesss",
   "fieldtype": "Data",
   "hidden": 0,
   "hide_border": 0,
   "hide_days": 0,
   "hide_seconds": 0,
   "idx": 21,
   "ignore_user_permissions": 0,
   "ignore_xss_filter": 0,
   "in_global_search": 0,
   "in_list_view": 0,
   "in_preview": 0,
   "in_standard_filter": 0,
   "insert_after": "custom_address",
   "is_system_generated": 0,
   "is_virtual": 0,
   "label": "Place of Businesss",
   "length": 0,
   "link_filters": null,
   "mandatory_depends_on": null,
   "modified": "2024-06-05 18:32:12.040015",
   "modified_by": "Administrator",
   "module": null,
   "name": "Efris Settings-custom_place_of_businesss",
   "no_copy": 0,
   "non_negative": 0,
   "options": null,
   "owner": "Administrator",
   "permlevel": 0,
   "precision": "",
   "print_hide": 0,
   "print_hide_if_no_value": 0,
   "print_width": null,
   "read_only": 0,
   "read_only_depends_on": null,
   "report_hide": 0,
   "reqd": 0,
   "search_index": 0,
   "show_dashboard": 0,
   "sort_options": 0,
   "translatable": 1,
   "unique": 0,
   "width": null
  },
  {
   "_assign": null,
   "_comments": null,
   "_liked_by": null,
   "_user_tags": null,
   "allow_in_quick_entry": 0,
   "allow_on_submit": 0,
   "bold": 0,
   "collapsible": 0,
   "collapsible_depends_on": null,
   "columns": 0,
   "creation": "2024-06-05 18:32:11.908927",
   "default": null,
   "depends_on": null,
   "description": null,
   "docstatus": 0,
   "dt": "Efris Settings",
   "fetch_from": null,
   "fetch_if_empty": 0,
   "fieldname": "custom_address",
   "fieldtype": "Data",
   "hidden": 0,
   "hide_border": 0,
   "hide_days": 0,
   "hide_seconds": 0,
   "idx": 20,
   "ignore_user_permissions": 0,
   "ignore_xss_filter": 0,
   "in_global_search": 0,
   "in_list_view": 0,
   "in_preview": 0,
   "in_standard_filter": 0,
   "insert_after": "custom_mobile_phone",
   "is_system_generated": 0,
   "is_virtual": 0,
   "label": "Address",
   "length": 0,
   "link_filters": null,
   "mandatory_depends_on": null,
   "modified": "2024-06-05 18:32:11.908927",
   "modified_by": "Administrator",
   "module": null,
   "name": "Efris Settings-custom_address",
   "no_copy": 0,
   "non_negative": 0,
   "options": null,
   "owner": "Administrator",
   "permlevel": 0,
   "precision": "",
   "print_hide": 0,
   "print_hide_if_no_value": 0,
   "print_width": null,
   "read_only": 0,
   "read_only_depends_on": null,
   "report_hide": 0,
   "reqd": 0,
   "search_index": 0,
   "show_dashboard": 0,
   "sort_options": 0,
   "translatable": 1,
   "unique": 0,
   "width": null
  },
  {
   "_assign": null,
   "_comments": null,
   "_liked_by": null,
   "_user_tags": null,
   "allow_in_quick_entry": 0,
   "allow_on_submit": 0,
   "bold": 0,
   "collapsible": 0,
   "collapsible_depends_on": null,
   "columns": 0,
   "creation": "2024-06-05 18:32:11.722086",
   "default": null,
   "depends_on": null,
   "description": null,
   "docstatus": 0,
   "dt": "Efris Settings",
   "fetch_from": null,
   "fetch_if_empty": 0,
   "fieldname": "custom_mobile_phone",
   "fieldtype": "Data",
   "hidden": 0,
   "hide_border": 0,
   "hide_days": 0,
   "hide_seconds": 0,
   "idx": 19,
   "ignore_user_permissions": 0,
   "ignore_xss_filter": 0,
   "in_global_search": 0,
   "in_list_view": 0,
   "in_preview": 0,
   "in_standard_filter": 0,
   "insert_after": "custom_brn",
   "is_system_generated": 0,
   "is_virtual": 0,
   "label": "Mobile Phone",
   "length": 0,
   "link_filters": null,
   "mandatory_depends_on": null,
   "modified": "2024-06-05 18:32:11.722086",
   "modified_by": "Administrator",
   "module": null,
   "name": "Efris Settings-custom_mobile_phone",
   "no_copy": 0,
   "non_negative": 0,
   "options": null,
   "owner": "Administrator",
   "permlevel": 0,
   "precision": "",
   "print_hide": 0,
   "print_hide_if_no_value": 0,
   "print_width": null,
   "read_only": 0,
   "read_only_depends_on": null,
   "report_hide": 0,
   "reqd": 0,
   "search_index": 0,
   "show_dashboard": 0,
   "sort_options": 0,
   "translatable": 1,
   "unique": 0,
   "width": null
  },
  {
   "_assign": null,
   "_comments": null,
   "_liked_by": null,
   "_user_tags": null,
   "allow_in_quick_entry": 0,
   "allow_on_submit": 0,
   "bold": 0,
   "collapsible": 0,
   "collapsible_depends_on": null,
   "columns": 0,
   "creation": "2024-06-05 18:32:11.585474",
   "default": null,
   "depends_on": null,
   "description": null,
   "docstatus": 0,
   "dt": "Efris Settings",
   "fetch_from": null,
   "fetch_if_empty": 0,
   "fieldname": "custom_brn",
   "fieldtype": "Data",
   "hidden": 0,
   "hide_border": 0,
   "hide_days": 0,
   "hide_seconds": 0,
   "idx": 18,
   "ignore_user_permissions": 0,
   "ignore_xss_filter": 0,
   "in_global_search": 0,
   "in_list_view": 0,
   "in_preview": 0,
   "in_standard_filter": 0,
   "insert_after": "custom_business_name",
   "is_system_generated": 0,
   "is_virtual": 0,
   "label": "BRN",
   "length": 0,
   "link_filters": null,
   "mandatory_depends_on": null,
   "modified": "2024-06-05 18:32:11.585474",
   "modified_by": "Administrator",
   "module": null,
   "name": "Efris Settings-custom_brn",
   "no_copy": 0,
   "non_negative": 0,
   "options": null,
   "owner": "Administrator",
   "permlevel": 0,
   "precision": "",
   "print_hide": 0,
   "print_hide_if_no_value": 0,
   "print_width": null,
   "read_only": 0,
   "read_only_depends_on": null,
   "report_hide": 0,
   "reqd": 0,
   "search_index": 0,
   "show_dashboard": 0,
   "sort_options": 0,
   "translatable": 1,
   "unique": 0,
   "width": null
  },
  {
   "_assign": null,
   "_comments": null,
   "_liked_by": null,
   "_user_tags": null,
   "allow_in_quick_entry": 0,
   "allow_on_submit": 0,
   "bold": 0,
   "collapsible": 0,
   "collapsible_depends_on": null,
   "columns": 0,
   "creation": "2024-06-05 18:32:11.463436",
   "default": null,
   "depends_on": null,
   "description": null,
   "docstatus": 0,
   "dt": "Efris Settings",
   "fetch_from": null,
   "fetch_if_empty": 0,
   "fieldname": "custom_business_name",
   "fieldtype": "Data",
   "hidden": 0,
   "hide_border": 0,
   "hide_days": 0,
   "hide_seconds": 0,
   "idx": 17,
   "ignore_user_permissions": 0,
   "ignore_xss_filter": 0,
   "in_global_search": 0,
   "in_list_view": 0,
   "in_preview": 0,
   "in_standard_filter": 0,
   "insert_after": "custom_tax_payers_tin",
   "is_system_generated": 0,
   "is_virtual": 0,
   "label": "Business Name",
   "length": 0,
   "link_filters": null,
   "mandatory_depends_on": null,
   "modified": "2024-06-05 18:32:11.463436",
   "modified_by": "Administrator",
   "module": null,
   "name": "Efris Settings-custom_business_name",
   "no_copy": 0,
   "non_negative": 0,
   "options": null,
   "owner": "Administrator",
   "permlevel": 0,
   "precision": "",
   "print_hide": 0,
   "print_hide_if_no_value": 0,
   "print_width": null,
   "read_only": 0,
   "read_only_depends_on": null,
   "report_hide": 0,
   "reqd": 0,
   "search_index": 0,
   "show_dashboard": 0,
   "sort_options": 0,
   "translatable": 1,
   "unique": 0,
   "width": null
  },
  {
   "_assign": null,
   "_comments": null,
   "_liked_by": null,
   "_user_tags": null,
   "allow_in_quick_entry": 0,
   "allow_on_submit": 0,
   "bold": 0,
   "collapsible": 0,
   "collapsible_depends_on": null,
   "columns": 0,
   "creation": "2024-06-05 18:32:11.339640",
   "default": null,
   "depends_on": null,
   "description": null,
   "docstatus": 0,
   "dt": "Efris Settings",
   "fetch_from": null,
   "fetch_if_empty": 0,
   "fieldname": "custom_column_break_f0yqn",
   "fieldtype": "Column Break",
   "hidden": 0,
   "hide_border": 0,
   "hide_days": 0,
   "hide_seconds": 0,
   "idx": 15,
   "ignore_user_permissions": 0,
   "ignore_xss_filter": 0,
   "in_global_search": 0,
   "in_list_view": 0,
   "in_preview": 0,
   "in_standard_filter": 0,
   "insert_after": "custom_email_address",
   "is_system_generated": 0,
   "is_virtual": 0,
   "label": "",
   "length": 0,
   "link_filters": null,
   "mandatory_depends_on": null,
   "modified": "2024-06-05 18:32:11.339640",
   "modified_by": "Administrator",
   "module": null,
   "name": "Efris Settings-custom_column_break_f0yqn",
   "no_copy": 0,
   "non_negative": 0,
   "options": null,
   "owner": "Administrator",
   "permlevel": 0,
   "precision": "",
   "print_hide": 0,
   "print_hide_if_no_value": 0,
   "print_width": null,
   "read_only": 0,
   "read_only_depends_on": null,
   "report_hide": 0,
   "reqd": 0,
   "search_index": 0,
   "show_dashboard": 0,
   "sort_options": 0,
   "translatable": 0,
   "unique": 0,
   "width": null
  },
  {
   "_assign": null,
   "_comments": null,
   "_liked_by": null,
   "_user_tags": null,
   "allow_in_quick_entry": 0,
   "allow_on_submit": 0,
   "bold": 0,
   "collapsible": 0,
   "collapsible_depends_on": null,
   "columns": 0,
   "creation": "2024-06-05 18:32:11.215404",
   "default": null,
   "depends_on": null,
   "description": null,
   "docstatus": 0,
   "dt": "Efris Settings",
   "fetch_from": null,
   "fetch_if_empty": 0,
   "fieldname": "custom_email_address",
   "fieldtype": "Data",
   "hidden": 0,
   "hide_border": 0,
   "hide_days": 0,
   "hide_seconds": 0,
   "idx": 14,
   "ignore_user_permissions": 0,
   "ignore_xss_filter": 0,
   "in_global_search": 0,
   "in_list_view": 0,
   "in_preview": 0,
   "in_standard_filter": 0,
   "insert_after": "custom_line_phone",
   "is_system_generated": 0,
   "is_virtual": 0,
   "label": "Email Address",
   "length": 0,
   "link_filters": null,
   "mandatory_depends_on": null,
   "modified": "2024-06-05 18:32:11.215404",
   "modified_by": "Administrator",
   "module": null,
   "name": "Efris Settings-custom_email_address",
   "no_copy": 0,
   "non_negative": 0,
   "options": null,
   "owner": "Administrator",
   "permlevel": 0,
   "precision": "",
   "print_hide": 0,
   "print_hide_if_no_value": 0,
   "print_width": null,
   "read_only": 0,
   "read_only_depends_on": null,
   "report_hide": 0,
   "reqd": 0,
   "search_index": 0,
   "show_dashboard": 0,
   "sort_options": 0,
   "translatable": 1,
   "unique": 0,
   "width": null
  },
  {
   "_assign": null,
   "_comments": null,
   "_liked_by": null,
   "_user_tags": null,
   "allow_in_quick_entry": 0,
   "allow_on_submit": 0,
   "bold": 0,
   "collapsible": 0,
   "collapsible_depends_on": null,
   "columns": 0,
   "creation": "2024-06-05 18:32:11.065099",
   "default": null,
   "depends_on": null,
   "description": null,
   "docstatus": 0,
   "dt": "Efris Settings",
   "fetch_from": null,
   "fetch_if_empty": 0,
   "fieldname": "custom_line_phone",
   "fieldtype": "Data",
   "hidden": 0,
   "hide_border": 0,
   "hide_days": 0,
   "hide_seconds": 0,
   "idx": 13,
   "ignore_user_permissions": 0,
   "ignore_xss_filter": 0,
   "in_global_search": 0,
   "in_list_view": 0,
   "in_preview": 0,
   "in_standard_filter": 0,
   "insert_after": "custom_branch_id",
   "is_system_generated": 0,
   "is_virtual": 0,
   "label": "Line Phone",
   "length": 0,
   "link_filters": null,
   "mandatory_depends_on": null,
   "modified": "2024-06-05 18:32:11.065099",
   "modified_by": "Administrator",
   "module": null,
   "name": "Efris Settings-custom_line_phone",
   "no_copy": 0,
   "non_negative": 0,
   "options": null,
   "owner": "Administrator",
   "permlevel": 0,
   "precision": "",
   "print_hide": 0,
   "print_hide_if_no_value": 0,
   "print_width": null,
   "read_only": 0,
   "read_only_depends_on": null,
   "report_hide": 0,
   "reqd": 0,
   "search_index": 0,
   "show_dashboard": 0,
   "sort_options": 0,
   "translatable": 1,
   "unique": 0,
   "width": null
  },
  {
   "_assign": null,
   "_comments": null,
   "_liked_by": null,
   "_user_tags": null,
   "allow_in_quick_entry": 0,
   "allow_on_submit": 0,
   "bold": 0,
   "collapsible": 0,
   "collapsible_depends_on": null,
   "columns": 0,
   "creation": "2024-06-05 18:32:10.861947",
   "default": null,
   "depends_on": null,
   "description": null,
   "docstatus": 0,
   "dt": "Efris Settings",
   "fetch_from": null,
   "fetch_if_empty": 0,
   "fieldname": "custom_branch_id",
   "fieldtype": "Data",
   "hidden": 0,
   "hide_border": 0,
   "hide_days": 0,
   "hide_seconds": 0,
   "idx": 12,
   "ignore_user_permissions": 0,
   "ignore_xss_filter": 0,
   "in_global_search": 0,
   "in_list_view": 0,
   "in_preview": 0,
   "in_standard_filter": 0,
   "insert_after": "custom_company",
   "is_system_generated": 0,
   "is_virtual": 0,
   "label": "Branch ID",
   "length": 0,
   "link_filters": null,
   "mandatory_depends_on": null,
   "modified": "2024-06-05 18:32:10.861947",
   "modified_by": "Administrator",
   "module": null,
   "name": "Efris Settings-custom_branch_id",
   "no_copy": 0,
   "non_negative": 0,
   "options": null,
   "owner": "Administrator",
   "permlevel": 0,
   "precision": "",
   "print_hide": 0,
   "print_hide_if_no_value": 0,
   "print_width": null,
   "read_only": 0,
   "read_only_depends_on": null,
   "report_hide": 0,
   "reqd": 0,
   "search_index": 0,
   "show_dashboard": 0,
   "sort_options": 0,
   "translatable": 1,
   "unique": 0,
   "width": null
  },
  {
   "_assign": null,
   "_comments": null,
   "_liked_by": null,
   "_user_tags": null,
   "allow_in_quick_entry": 0,
   "allow_on_submit": 0,
   "bold": 0,
   "collapsible": 0,
   "collapsible_depends_on": null,
   "columns": 0,
   "creation": "2024-06-05 18:32:10.550836",
   "default": null,
   "depends_on": null,
   "description": null,
   "docstatus": 0,
   "dt": "Efris Settings",
   "fetch_from": null,
   "fetch_if_empty": 0,
   "fieldname": "custom_company_settings",
   "fieldtype": "Section Break",
   "hidden": 0,
   "hide_border": 0,
   "hide_days": 0,
   "hide_seconds": 0,
   "idx": 9,
   "ignore_user_permissions": 0,
   "ignore_xss_filter": 0,
   "in_global_search": 0,
   "in_list_view": 0,
   "in_preview": 0,
   "in_standard_filter": 0,
   "insert_after": "custom_device_number",
   "is_system_generated": 0,
   "is_virtual": 0,
   "label": "Company settings",
   "length": 0,
   "link_filters": null,
   "mandatory_depends_on": null,
   "modified": "2024-06-05 18:32:10.550836",
   "modified_by": "Administrator",
   "module": null,
   "name": "Efris Settings-custom_company_settings",
   "no_copy": 0,
   "non_negative": 0,
   "options": null,
   "owner": "Administrator",
   "permlevel": 0,
   "precision": "",
   "print_hide": 0,
   "print_hide_if_no_value": 0,
   "print_width": null,
   "read_only": 0,
   "read_only_depends_on": null,
   "report_hide": 0,
   "reqd": 0,
   "search_index": 0,
   "show_dashboard": 0,
   "sort_options": 0,
   "translatable": 0,
   "unique": 0,
   "width": null
  },
  {
   "_assign": null,
   "_comments": null,
   "_liked_by": null,
   "_user_tags": null,
   "allow_in_quick_entry": 0,
   "allow_on_submit": 0,
   "bold": 0,
   "collapsible": 0,
   "collapsible_depends_on": null,
   "columns": 0,
   "creation": "2024-06-05 09:20:27.272545",
   "default": null,
   "depends_on": null,
   "description": null,
   "docstatus": 0,
   "dt": "Efris Settings",
   "fetch_from": null,
   "fetch_if_empty": 0,
   "fieldname": "custom_purchase_information_submission_frequency",
   "fieldtype": "Select",
   "hidden": 0,
   "hide_border": 0,
   "hide_days": 0,
   "hide_seconds": 0,
   "idx": 28,
   "ignore_user_permissions": 0,
   "ignore_xss_filter": 0,
   "in_global_search": 0,
   "in_list_view": 0,
   "in_preview": 0,
   "in_standard_filter": 0,
   "insert_after": "custom_column_break_eygkz",
   "is_system_generated": 0,
   "is_virtual": 0,
   "label": "Purchase information Submission frequency",
   "length": 0,
   "link_filters": null,
   "mandatory_depends_on": null,
   "modified": "2024-06-05 09:20:27.272545",
   "modified_by": "Administrator",
   "module": null,
   "name": "Efris Settings-custom_purchase_information_submission_frequency",
   "no_copy": 0,
   "non_negative": 0,
   "options": null,
   "owner": "Administrator",
   "permlevel": 0,
   "precision": "",
   "print_hide": 0,
   "print_hide_if_no_value": 0,
   "print_width": null,
   "read_only": 0,
   "read_only_depends_on": null,
   "report_hide": 0,
   "reqd": 0,
   "search_index": 0,
   "show_dashboard": 0,
   "sort_options": 0,
   "translatable": 1,
   "unique": 0,
   "width": null
  },
  {
   "_assign": null,
   "_comments": null,
   "_liked_by": null,
   "_user_tags": null,
   "allow_in_quick_entry": 0,
   "allow_on_submit": 0,
   "bold": 0,
   "collapsible": 0,
   "collapsible_depends_on": null,
   "columns": 0,
   "creation": "2024-06-05 09:20:27.145907",
   "default": null,
   "depends_on": null,
   "description": null,
   "docstatus": 0,
   "dt": "Efris Settings",
   "fetch_from": null,
   "fetch_if_empty": 0,
   "fieldname": "custom_column_break_eygkz",
   "fieldtype": "Column Break",
   "hidden": 0,
   "hide_border": 0,
   "hide_days": 0,
   "hide_seconds": 0,
   "idx": 27,
   "ignore_user_permissions": 0,
   "ignore_xss_filter": 0,
   "in_global_search": 0,
   "in_list_view": 0,
   "in_preview": 0,
   "in_standard_filter": 0,
   "insert_after": "custom_stock_information_submission_frequency",
   "is_system_generated": 0,
   "is_virtual": 0,
   "label": "",
   "length": 0,
   "link_filters": null,
   "mandatory_depends_on": null,
   "modified": "2024-06-05 09:20:27.145907",
   "modified_by": "Administrator",
   "module": null,
   "name": "Efris Settings-custom_column_break_eygkz",
   "no_copy": 0,
   "non_negative": 0,
   "options": null,
   "owner": "Administrator",
   "permlevel": 0,
   "precision": "",
   "print_hide": 0,
   "print_hide_if_no_value": 0,
   "print_width": null,
   "read_only": 0,
   "read_only_depends_on": null,
   "report_hide": 0,
   "reqd": 0,
   "search_index": 0,
   "show_dashboard": 0,
   "sort_options": 0,
   "translatable": 0,
   "unique": 0,
   "width": null
  },
  {
   "_assign": null,
   "_comments": null,
   "_liked_by": null,
   "_user_tags": null,
   "allow_in_quick_entry": 0,
   "allow_on_submit": 0,
   "bold": 0,
   "collapsible": 0,
   "collapsible_depends_on": null,
   "columns": 0,
   "creation": "2024-06-05 09:20:26.983710",
   "default": null,
   "depends_on": null,
   "description": null,
   "docstatus": 0,
   "dt": "Efris Settings",
   "fetch_from": null,
   "fetch_if_empty": 0,
   "fieldname": "custom_stock_information_submission_frequency",
   "fieldtype": "Select",
   "hidden": 0,
   "hide_border": 0,
   "hide_days": 0,
   "hide_seconds": 0,
   "idx": 26,
   "ignore_user_permissions": 0,
   "ignore_xss_filter": 0,
   "in_global_search": 0,
   "in_list_view": 0,
   "in_preview": 0,
   "in_standard_filter": 0,
   "insert_after": "custom_column_break_9mqzu",
   "is_system_generated": 0,
   "is_virtual": 0,
   "label": "Stock Information Submission Frequency",
   "length": 0,
   "link_filters": null,
   "mandatory_depends_on": null,
   "modified": "2024-06-05 09:20:26.983710",
   "modified_by": "Administrator",
   "module": null,
   "name": "Efris Settings-custom_stock_information_submission_frequency",
   "no_copy": 0,
   "non_negative": 0,
   "options": null,
   "owner": "Administrator",
   "permlevel": 0,
   "precision": "",
   "print_hide": 0,
   "print_hide_if_no_value": 0,
   "print_width": null,
   "read_only": 0,
   "read_only_depends_on": null,
   "report_hide": 0,
   "reqd": 0,
   "search_index": 0,
   "show_dashboard": 0,
   "sort_options": 0,
   "translatable": 1,
   "unique": 0,
   "width": null
  },
  {
   "_assign": null,
   "_comments": null,
   "_liked_by": null,
   "_user_tags": null,
   "allow_in_quick_entry": 0,
   "allow_on_submit": 0,
   "bold": 0,
   "collapsible": 0,
   "collapsible_depends_on": null,
   "columns": 0,
   "creation": "2024-06-05 09:20:26.870456",
   "default": null,
   "depends_on": null,
   "description": null,
   "docstatus": 0,
   "dt": "Efris Settings",
   "fetch_from": null,
   "fetch_if_empty": 0,
   "fieldname": "custom_column_break_9mqzu",
   "fieldtype": "Column Break",
   "hidden": 0,
   "hide_border": 0,
   "hide_days": 0,
   "hide_seconds": 0,
   "idx": 25,
   "ignore_user_permissions": 0,
   "ignore_xss_filter": 0,
   "in_global_search": 0,
   "in_list_view": 0,
   "in_preview": 0,
   "in_standard_filter": 0,
   "insert_after": "custom_sales_information_submission_frequency",
   "is_system_generated": 0,
   "is_virtual": 0,
   "label": "",
   "length": 0,
   "link_filters": null,
   "mandatory_depends_on": null,
   "modified": "2024-06-05 09:20:26.870456",
   "modified_by": "Administrator",
   "module": null,
   "name": "Efris Settings-custom_column_break_9mqzu",
   "no_copy": 0,
   "non_negative": 0,
   "options": null,
   "owner": "Administrator",
   "permlevel": 0,
   "precision": "",
   "print_hide": 0,
   "print_hide_if_no_value": 0,
   "print_width": null,
   "read_only": 0,
   "read_only_depends_on": null,
   "report_hide": 0,
   "reqd": 0,
   "search_index": 0,
   "show_dashboard": 0,
   "sort_options": 0,
   "translatable": 0,
   "unique": 0,
   "width": null
  },
  {
   "_assign": null,
   "_comments": null,
   "_liked_by": null,
   "_user_tags": null,
   "allow_in_quick_entry": 0,
   "allow_on_submit": 0,
   "bold": 0,
   "collapsible": 0,
   "collapsible_depends_on": null,
   "columns": 0,
   "creation": "2024-06-05 09:20:26.723702",
   "default": null,
   "depends_on": null,
   "description": null,
   "docstatus": 0,
   "dt": "Efris Settings",
   "fetch_from": null,
   "fetch_if_empty": 0,
   "fieldname": "custom_sales_information_submission_frequency",
   "fieldtype": "Select",
   "hidden": 0,
   "hide_border": 0,
   "hide_days": 0,
   "hide_seconds": 0,
   "idx": 24,
   "ignore_user_permissions": 0,
   "ignore_xss_filter": 0,
   "in_global_search": 0,
   "in_list_view": 0,
   "in_preview": 0,
   "in_standard_filter": 0,
   "insert_after": "custom_frequency_of_communication_of_the_efris_server",
   "is_system_generated": 0,
   "is_virtual": 0,
   "label": "Sales Information Submission Frequency",
   "length": 0,
   "link_filters": null,
   "mandatory_depends_on": null,
   "modified": "2024-06-05 09:20:26.723702",
   "modified_by": "Administrator",
   "module": null,
   "name": "Efris Settings-custom_sales_information_submission_frequency",
   "no_copy": 0,
   "non_negative": 0,
   "options": null,
   "owner": "Administrator",
   "permlevel": 0,
   "precision": "",
   "print_hide": 0,
   "print_hide_if_no_value": 0,
   "print_width": null,
   "read_only": 0,
   "read_only_depends_on": null,
   "report_hide": 0,
   "reqd": 0,
   "search_index": 0,
   "show_dashboard": 0,
   "sort_options": 0,
   "translatable": 1,
   "unique": 0,
   "width": null
  },
  {
   "_assign": null,
   "_comments": null,
   "_liked_by": null,
   "_user_tags": null,
   "allow_in_quick_entry": 0,
   "allow_on_submit": 0,
   "bold": 0,
   "collapsible": 0,
   "collapsible_depends_on": null,
   "columns": 0,
   "creation": "2024-06-05 09:20:26.603187",
   "default": null,
   "depends_on": null,
   "description": null,
   "docstatus": 0,
   "dt": "Efris Settings",
   "fetch_from": null,
   "fetch_if_empty": 0,
   "fieldname": "custom_frequency_of_communication_of_the_efris_server",
   "fieldtype": "Section Break",
   "hidden": 0,
   "hide_border": 0,
   "hide_days": 0,
   "hide_seconds": 0,
   "idx": 23,
   "ignore_user_permissions": 0,
   "ignore_xss_filter": 0,
   "in_global_search": 0,
   "in_list_view": 0,
   "in_preview": 0,
   "in_standard_filter": 0,
   "insert_after": "custom_submission_frequency_",
   "is_system_generated": 0,
   "is_virtual": 0,
   "label": "Frequency of Communication of the EFRIS Server",
   "length": 0,
   "link_filters": null,
   "mandatory_depends_on": null,
   "modified": "2024-06-05 09:20:26.603187",
   "modified_by": "Administrator",
   "module": null,
   "name": "Efris Settings-custom_frequency_of_communication_of_the_efris_server",
   "no_copy": 0,
   "non_negative": 0,
   "options": null,
   "owner": "Administrator",
   "permlevel": 0,
   "precision": "",
   "print_hide": 0,
   "print_hide_if_no_value": 0,
   "print_width": null,
   "read_only": 0,
   "read_only_depends_on": null,
   "report_hide": 0,
   "reqd": 0,
   "search_index": 0,
   "show_dashboard": 0,
   "sort_options": 0,
   "translatable": 0,
   "unique": 0,
   "width": null
  },
  {
   "_assign": null,
   "_comments": null,
   "_liked_by": null,
   "_user_tags": null,
   "allow_in_quick_entry": 0,
   "allow_on_submit": 0,
   "bold": 0,
   "collapsible": 0,
   "collapsible_depends_on": null,
   "columns": 0,
   "creation": "2024-06-05 09:20:26.469510",
   "default": null,
   "depends_on": null,
   "description": null,
   "docstatus": 0,
   "dt": "Efris Settings",
   "fetch_from": null,
   "fetch_if_empty": 0,
   "fieldname": "custom_submission_frequency_",
   "fieldtype": "Tab Break",
   "hidden": 0,
   "hide_border": 0,
   "hide_days": 0,
   "hide_seconds": 0,
   "idx": 22,
   "ignore_user_permissions": 0,
   "ignore_xss_filter": 0,
   "in_global_search": 0,
   "in_list_view": 0,
   "in_preview": 0,
   "in_standard_filter": 0,
   "insert_after": "custom_place_of_businesss",
   "is_system_generated": 0,
   "is_virtual": 0,
   "label": "Submission Frequency ",
   "length": 0,
   "link_filters": null,
   "mandatory_depends_on": null,
   "modified": "2024-06-05 09:20:26.469510",
   "modified_by": "Administrator",
   "module": null,
   "name": "Efris Settings-custom_submission_frequency_",
   "no_copy": 0,
   "non_negative": 0,
   "options": null,
   "owner": "Administrator",
   "permlevel": 0,
   "precision": "",
   "print_hide": 0,
   "print_hide_if_no_value": 0,
   "print_width": null,
   "read_only": 0,
   "read_only_depends_on": null,
   "report_hide": 0,
   "reqd": 0,
   "search_index": 0,
   "show_dashboard": 0,
   "sort_options": 0,
   "translatable": 0,
   "unique": 0,
   "width": null
  },
  {
   "_assign": null,
   "_comments": null,
   "_liked_by": null,
   "_user_tags": null,
   "allow_in_quick_entry": 0,
   "allow_on_submit": 0,
   "bold": 0,
   "collapsible": 0,
   "collapsible_depends_on": null,
   "columns": 0,
   "creation": "2024-06-05 09:20:26.269901",
   "default": null,
   "depends_on": null,
   "description": "EFRIS Offline Enabler device number TCS...........",
   "docstatus": 0,
   "dt": "Efris Settings",
   "fetch_from": null,
   "fetch_if_empty": 0,
   "fieldname": "custom_device_number",
   "fieldtype": "Data",
   "hidden": 0,
   "hide_border": 0,
   "hide_days": 0,
   "hide_seconds": 0,
   "idx": 8,
   "ignore_user_permissions": 0,
   "ignore_xss_filter": 0,
   "in_global_search": 0,
   "in_list_view": 0,
   "in_preview": 0,
   "in_standard_filter": 0,
   "insert_after": "custom_column_break_x3yxt",
   "is_system_generated": 0,
   "is_virtual": 0,
   "label": "Device Number",
   "length": 0,
   "link_filters": null,
   "mandatory_depends_on": null,
   "modified": "2024-06-05 09:20:26.269901",
   "modified_by": "Administrator",
   "module": null,
   "name": "Efris Settings-custom_device_number",
   "no_copy": 0,
   "non_negative": 0,
   "options": null,
   "owner": "Administrator",
   "permlevel": 0,
   "precision": "",
   "print_hide": 0,
   "print_hide_if_no_value": 0,
   "print_width": null,
   "read_only": 0,
   "read_only_depends_on": null,
   "report_hide": 0,
   "reqd": 1,
   "search_index": 0,
   "show_dashboard": 0,
   "sort_options": 0,
   "translatable": 1,
   "unique": 0,
   "width": null
  },
  {
   "_assign": null,
   "_comments": null,
   "_liked_by": null,
   "_user_tags": null,
   "allow_in_quick_entry": 0,
   "allow_on_submit": 0,
   "bold": 0,
   "collapsible": 0,
   "collapsible_depends_on": null,
   "columns": 0,
   "creation": "2024-06-05 09:20:26.134247",
   "default": null,
   "depends_on": null,
   "description": null,
   "docstatus": 0,
   "dt": "Efris Settings",
   "fetch_from": null,
   "fetch_if_empty": 0,
   "fieldname": "custom_legal_name",
   "fieldtype": "Data",
   "hidden": 0,
   "hide_border": 0,
   "hide_days": 0,
   "hide_seconds": 0,
   "idx": 10,
   "ignore_user_permissions": 0,
   "ignore_xss_filter": 0,
   "in_global_search": 0,
   "in_list_view": 0,
   "in_preview": 0,
   "in_standard_filter": 0,
   "insert_after": "custom_company_settings",
   "is_system_generated": 0,
   "is_virtual": 0,
   "label": "Legal Name",
   "length": 0,
   "link_filters": null,
   "mandatory_depends_on": null,
   "modified": "2024-06-05 09:20:26.134247",
   "modified_by": "Administrator",
   "module": null,
   "name": "Efris Settings-custom_legal_name",
   "no_copy": 0,
   "non_negative": 0,
   "options": null,
   "owner": "Administrator",
   "permlevel": 0,
   "precision": "",
   "print_hide": 0,
   "print_hide_if_no_value": 0,
   "print_width": null,
   "read_only": 0,
   "read_only_depends_on": null,
   "report_hide": 0,
   "reqd": 1,
   "search_index": 0,
   "show_dashboard": 0,
   "sort_options": 0,
   "translatable": 1,
   "unique": 1,
   "width": null
  },
  {
   "_assign": null,
   "_comments": null,
   "_liked_by": null,
   "_user_tags": null,
   "allow_in_quick_entry": 0,
   "allow_on_submit": 0,
   "bold": 0,
   "collapsible": 0,
   "collapsible_depends_on": null,
   "columns": 0,
   "creation": "2024-06-05 09:20:26.020198",
   "default": null,
   "depends_on": null,
   "description": null,
   "docstatus": 0,
   "dt": "Efris Settings",
   "fetch_from": null,
   "fetch_if_empty": 0,
   "fieldname": "custom_column_break_x3yxt",
   "fieldtype": "Column Break",
   "hidden": 0,
   "hide_border": 0,
   "hide_days": 0,
   "hide_seconds": 0,
   "idx": 7,
   "ignore_user_permissions": 0,
   "ignore_xss_filter": 0,
   "in_global_search": 0,
   "in_list_view": 0,
   "in_preview": 0,
   "in_standard_filter": 0,
   "insert_after": "custom_server_url",
   "is_system_generated": 0,
   "is_virtual": 0,
   "label": "",
   "length": 0,
   "link_filters": null,
   "mandatory_depends_on": null,
   "modified": "2024-06-05 09:20:26.020198",
   "modified_by": "Administrator",
   "module": null,
   "name": "Efris Settings-custom_column_break_x3yxt",
   "no_copy": 0,
   "non_negative": 0,
   "options": null,
   "owner": "Administrator",
   "permlevel": 0,
   "precision": "",
   "print_hide": 0,
   "print_hide_if_no_value": 0,
   "print_width": null,
   "read_only": 0,
   "read_only_depends_on": null,
   "report_hide": 0,
   "reqd": 0,
   "search_index": 0,
   "show_dashboard": 0,
   "sort_options": 0,
   "translatable": 0,
   "unique": 0,
   "width": null
  },
  {
   "_assign": null,
   "_comments": null,
   "_liked_by": null,
   "_user_tags": null,
   "allow_in_quick_entry": 0,
   "allow_on_submit": 0,
   "bold": 0,
   "collapsible": 0,
   "collapsible_depends_on": null,
   "columns": 0,
   "creation": "2024-06-05 09:20:25.890015",
   "default": null,
   "depends_on": null,
   "description": "TIN for the Company asociated with EFRIS Account",
   "docstatus": 0,
   "dt": "Efris Settings",
   "fetch_from": null,
   "fetch_if_empty": 0,
   "fieldname": "custom_tax_payers_tin",
   "fieldtype": "Data",
   "hidden": 0,
   "hide_border": 0,
   "hide_days": 0,
   "hide_seconds": 0,
   "idx": 16,
   "ignore_user_permissions": 0,
   "ignore_xss_filter": 0,
   "in_global_search": 0,
   "in_list_view": 0,
   "in_preview": 0,
   "in_standard_filter": 0,
   "insert_after": "custom_column_break_f0yqn",
   "is_system_generated": 0,
   "is_virtual": 0,
   "label": "Tax Payer's TIN",
   "length": 0,
   "link_filters": null,
   "mandatory_depends_on": null,
   "modified": "2024-06-05 09:20:25.890015",
   "modified_by": "Administrator",
   "module": null,
   "name": "Efris Settings-custom_tax_payers_tin",
   "no_copy": 0,
   "non_negative": 0,
   "options": null,
   "owner": "Administrator",
   "permlevel": 0,
   "precision": "",
   "print_hide": 0,
   "print_hide_if_no_value": 0,
   "print_width": null,
   "read_only": 0,
   "read_only_depends_on": null,
   "report_hide": 0,
   "reqd": 1,
   "search_index": 0,
   "show_dashboard": 0,
   "sort_options": 0,
   "translatable": 1,
   "unique": 0,
   "width": null
  },
  {
   "_assign": null,
   "_comments": null,
   "_liked_by": null,
   "_user_tags": null,
   "allow_in_quick_entry": 0,
   "allow_on_submit": 0,
   "bold": 0,
   "collapsible": 0,
   "collapsible_depends_on": null,
   "columns": 0,
   "creation": "2024-06-05 09:20:25.588324",
   "default": null,
   "depends_on": null,
   "description": "EFRIS Offline Enabler url, Kindly don't fill in if you're not sure",
   "docstatus": 0,
   "dt": "Efris Settings",
   "fetch_from": null,
   "fetch_if_empty": 0,
   "fieldname": "custom_server_url",
   "fieldtype": "Data",
   "hidden": 0,
   "hide_border": 0,
   "hide_days": 0,
   "hide_seconds": 0,
   "idx": 6,
   "ignore_user_permissions": 0,
   "ignore_xss_filter": 0,
   "in_global_search": 0,
   "in_list_view": 0,
   "in_preview": 0,
   "in_standard_filter": 0,
   "insert_after": "custom_settings_definition",
   "is_system_generated": 0,
   "is_virtual": 0,
   "label": "Server URL",
   "length": 0,
   "link_filters": null,
   "mandatory_depends_on": null,
   "modified": "2024-06-05 09:20:25.588324",
   "modified_by": "Administrator",
   "module": null,
   "name": "Efris Settings-custom_server_url",
   "no_copy": 0,
   "non_negative": 0,
   "options": null,
   "owner": "Administrator",
   "permlevel": 0,
   "precision": "",
   "print_hide": 0,
   "print_hide_if_no_value": 0,
   "print_width": null,
   "read_only": 0,
   "read_only_depends_on": null,
   "report_hide": 0,
   "reqd": 1,
   "search_index": 0,
   "show_dashboard": 0,
   "sort_options": 0,
   "translatable": 1,
   "unique": 0,
   "width": null
  },
  {
   "_assign": null,
   "_comments": null,
   "_liked_by": null,
   "_user_tags": null,
   "allow_in_quick_entry": 0,
   "allow_on_submit": 0,
   "bold": 0,
   "collapsible": 0,
   "collapsible_depends_on": null,
   "columns": 0,
   "creation": "2024-06-05 09:20:25.467214",
   "default": null,
   "depends_on": null,
   "description": null,
   "docstatus": 0,
   "dt": "Efris Settings",
   "fetch_from": null,
   "fetch_if_empty": 0,
   "fieldname": "custom_settings_definition",
   "fieldtype": "Section Break",
   "hidden": 0,
   "hide_border": 0,
   "hide_days": 0,
   "hide_seconds": 0,
   "idx": 5,
   "ignore_user_permissions": 0,
   "ignore_xss_filter": 0,
   "in_global_search": 0,
   "in_list_view": 0,
   "in_preview": 0,
   "in_standard_filter": 0,
   "insert_after": "custom_is_active",
   "is_system_generated": 0,
   "is_virtual": 0,
   "label": "Settings Definition",
   "length": 0,
   "link_filters": null,
   "mandatory_depends_on": null,
   "modified": "2024-06-05 09:20:25.467214",
   "modified_by": "Administrator",
   "module": null,
   "name": "Efris Settings-custom_settings_definition",
   "no_copy": 0,
   "non_negative": 0,
   "options": null,
   "owner": "Administrator",
   "permlevel": 0,
   "precision": "",
   "print_hide": 0,
   "print_hide_if_no_value": 0,
   "print_width": null,
   "read_only": 0,
   "read_only_depends_on": null,
   "report_hide": 0,
   "reqd": 0,
   "search_index": 0,
   "show_dashboard": 0,
   "sort_options": 0,
   "translatable": 0,
   "unique": 0,
   "width": null
  },
  {
   "_assign": null,
   "_comments": null,
   "_liked_by": null,
   "_user_tags": null,
   "allow_in_quick_entry": 0,
   "allow_on_submit": 0,
   "bold": 0,
   "collapsible": 0,
   "collapsible_depends_on": null,
   "columns": 0,
   "creation": "2024-06-05 09:20:25.287157",
   "default": null,
   "depends_on": null,
   "description": null,
   "docstatus": 0,
   "dt": "Efris Settings",
   "fetch_from": null,
   "fetch_if_empty": 0,
   "fieldname": "custom_is_active",
   "fieldtype": "Check",
   "hidden": 0,
   "hide_border": 0,
   "hide_days": 0,
   "hide_seconds": 0,
   "idx": 4,
   "ignore_user_permissions": 0,
   "ignore_xss_filter": 0,
   "in_global_search": 0,
   "in_list_view": 0,
   "in_preview": 0,
   "in_standard_filter": 0,
   "insert_after": "custom_column_break_zih13",
   "is_system_generated": 0,
   "is_virtual": 0,
   "label": "Is Active",
   "length": 0,
   "link_filters": null,
   "mandatory_depends_on": null,
   "modified": "2024-06-05 09:20:25.287157",
   "modified_by": "Administrator",
   "module": null,
   "name": "Efris Settings-custom_is_active",
   "no_copy": 0,
   "non_negative": 0,
   "options": null,
   "owner": "Administrator",
   "permlevel": 0,
   "precision": "",
   "print_hide": 0,
   "print_hide_if_no_value": 0,
   "print_width": null,
   "read_only": 0,
   "read_only_depends_on": null,
   "report_hide": 0,
   "reqd": 0,
   "search_index": 0,
   "show_dashboard": 0,
   "sort_options": 0,
   "translatable": 0,
   "unique": 0,
   "width": null
  },
  {
   "_assign": null,
   "_comments": null,
   "_liked_by": null,
   "_user_tags": null,
   "allow_in_quick_entry": 0,
   "allow_on_submit": 0,
   "bold": 0,
   "collapsible": 0,
   "collapsible_depends_on": null,
   "columns": 0,
   "creation": "2024-06-05 09:20:25.055537",
   "default": null,
   "depends_on": null,
   "description": null,
   "docstatus": 0,
   "dt": "Efris Settings",
   "fetch_from": null,
   "fetch_if_empty": 0,
   "fieldname": "custom_column_break_zih13",
   "fieldtype": "Column Break",
   "hidden": 0,
   "hide_border": 0,
   "hide_days": 0,
   "hide_seconds": 0,
   "idx": 3,
   "ignore_user_permissions": 0,
   "ignore_xss_filter": 0,
   "in_global_search": 0,
   "in_list_view": 0,
   "in_preview": 0,
   "in_standard_filter": 0,
   "insert_after": "custom_sandbox",
   "is_system_generated": 0,
   "is_virtual": 0,
   "label": "",
   "length": 0,
   "link_filters": null,
   "mandatory_depends_on": null,
   "modified": "2024-06-05 09:20:25.055537",
   "modified_by": "Administrator",
   "module": null,
   "name": "Efris Settings-custom_column_break_zih13",
   "no_copy": 0,
   "non_negative": 0,
   "options": null,
   "owner": "Administrator",
   "permlevel": 0,
   "precision": "",
   "print_hide": 0,
   "print_hide_if_no_value": 0,
   "print_width": null,
   "read_only": 0,
   "read_only_depends_on": null,
   "report_hide": 0,
   "reqd": 0,
   "search_index": 0,
   "show_dashboard": 0,
   "sort_options": 0,
   "translatable": 0,
   "unique": 0,
   "width": null
  },
  {
   "_assign": null,
   "_comments": null,
   "_liked_by": null,
   "_user_tags": null,
   "allow_in_quick_entry": 0,
   "allow_on_submit": 0,
   "bold": 0,
   "collapsible": 0,
   "collapsible_depends_on": null,
   "columns": 0,
   "creation": "2024-06-05 09:20:24.890212",
   "default": null,
   "depends_on": null,
   "description": "Marks the environment as either sandbox or production environment",
   "docstatus": 0,
   "dt": "Efris Settings",
   "fetch_from": null,
   "fetch_if_empty": 0,
   "fieldname": "custom_sandbox",
   "fieldtype": "Check",
   "hidden": 0,
   "hide_border": 0,
   "hide_days": 0,
   "hide_seconds": 0,
   "idx": 2,
   "ignore_user_permissions": 0,
   "ignore_xss_filter": 0,
   "in_global_search": 0,
   "in_list_view": 0,
   "in_preview": 0,
   "in_standard_filter": 0,
   "insert_after": "custom_envrionment",
   "is_system_generated": 0,
   "is_virtual": 0,
   "label": "Sandbox",
   "length": 0,
   "link_filters": null,
   "mandatory_depends_on": null,
   "modified": "2024-06-05 09:20:24.890212",
   "modified_by": "Administrator",
   "module": null,
   "name": "Efris Settings-custom_sandbox",
   "no_copy": 0,
   "non_negative": 0,
   "options": null,
   "owner": "Administrator",
   "permlevel": 0,
   "precision": "",
   "print_hide": 0,
   "print_hide_if_no_value": 0,
   "print_width": null,
   "read_only": 0,
   "read_only_depends_on": null,
   "report_hide": 0,
   "reqd": 0,
   "search_index": 0,
   "show_dashboard": 0,
   "sort_options": 0,
   "translatable": 0,
   "unique": 0,
   "width": null
  },
  {
   "_assign": null,
   "_comments": null,
   "_liked_by": null,
   "_user_tags": null,
   "allow_in_quick_entry": 0,
   "allow_on_submit": 0,
   "bold": 0,
   "collapsible": 0,
   "collapsible_depends_on": null,
   "columns": 0,
   "creation": "2024-06-05 09:20:24.709760",
   "default": null,
   "depends_on": null,
   "description": null,
   "docstatus": 0,
   "dt": "Efris Settings",
   "fetch_from": null,
   "fetch_if_empty": 0,
   "fieldname": "custom_envrionment",
   "fieldtype": "Section Break",
   "hidden": 0,
   "hide_border": 0,
   "hide_days": 0,
   "hide_seconds": 0,
   "idx": 1,
   "ignore_user_permissions": 0,
   "ignore_xss_filter": 0,
   "in_global_search": 0,
   "in_list_view": 0,
   "in_preview": 0,
   "in_standard_filter": 0,
   "insert_after": null,
   "is_system_generated": 0,
   "is_virtual": 0,
   "label": "Envrionment",
   "length": 0,
   "link_filters": null,
   "mandatory_depends_on": null,
   "modified": "2024-06-05 09:20:24.709760",
   "modified_by": "Administrator",
   "module": null,
   "name": "Efris Settings-custom_envrionment",
   "no_copy": 0,
   "non_negative": 0,
   "options": null,
   "owner": "Administrator",
   "permlevel": 0,
   "precision": "",
   "print_hide": 0,
   "print_hide_if_no_value": 0,
   "print_width": null,
   "read_only": 0,
   "read_only_depends_on": null,
   "report_hide": 0,
   "reqd": 0,
   "search_index": 0,
   "show_dashboard": 0,
   "sort_options": 0,
   "translatable": 0,
   "unique": 0,
   "width": null
  }
 ],
 "custom_perms": [],
 "doctype": "Efris Settings",
 "links": [],
 "property_setters": [
  {
   "_assign": null,
   "_comments": null,
   "_liked_by": null,
   "_user_tags": null,
   "creation": "2024-06-20 10:13:26.378244",
   "default_value": null,
   "doc_type": "Efris Settings",
   "docstatus": 0,
   "doctype_or_field": "DocType",
   "field_name": null,
   "idx": 0,
   "is_system_generated": 0,
   "modified": "2024-06-20 10:13:26.378244",
   "modified_by": "Administrator",
   "module": null,
   "name": "Efris Settings-main-field_order",
   "owner": "Administrator",
   "property": "field_order",
   "property_type": "Data",
   "row_name": null,
   "value": "[\"custom_envrionment\", \"custom_sandbox\", \"custom_column_break_zih13\", \"custom_is_active\", \"custom_settings_definition\", \"custom_server_url\", \"custom_column_break_x3yxt\", \"custom_device_number\", \"custom_company_settings\", \"custom_legal_name\", \"custom_company\", \"custom_branch_id\", \"custom_line_phone\", \"custom_email_address\", \"custom_column_break_f0yqn\", \"custom_tax_payers_tin\", \"custom_business_name\", \"custom_brn\", \"custom_mobile_phone\", \"custom_address\", \"custom_place_of_businesss\", \"custom_submission_frequency_\", \"custom_frequency_of_communication_of_the_efris_server\", \"custom_sales_information_submission_frequency\", \"custom_column_break_9mqzu\", \"custom_stock_information_submission_frequency\", \"custom_column_break_eygkz\", \"custom_purchase_information_submission_frequency\", \"section_break_9p9v\", \"amended_from\"]"
  },
  {
   "_assign": null,
   "_comments": null,
   "_liked_by": null,
   "_user_tags": null,
   "creation": "2024-06-20 10:13:26.298781",
   "default_value": null,
   "doc_type": "Efris Settings",
   "docstatus": 0,
   "doctype_or_field": "DocType",
   "field_name": null,
   "idx": 0,
   "is_system_generated": 0,
   "modified": "2024-06-20 10:13:26.298781",
   "modified_by": "Administrator",
   "module": null,
   "name": "Efris Settings-main-autoname",
   "owner": "Administrator",
   "property": "autoname",
   "property_type": "Data",
   "row_name": null,
   "value": "field:custom_company"
  },
  {
   "_assign": null,
   "_comments": null,
   "_liked_by": null,
   "_user_tags": null,
   "creation": "2024-06-19 15:37:32.328057",
   "default_value": null,
   "doc_type": "Efris Settings",
   "docstatus": 0,
   "doctype_or_field": "DocType",
   "field_name": null,
   "idx": 0,
   "is_system_generated": 0,
   "modified": "2024-06-19 15:37:32.328057",
   "modified_by": "Administrator",
   "module": null,
   "name": "Efris Settings-main-naming_rule",
   "owner": "Administrator",
   "property": "naming_rule",
   "property_type": "Data",
   "row_name": null,
   "value": "By fieldname"
  }
 ],
 "sync_on_migrate": 1
}