{
 "custom_fields": [],
 "custom_perms": [],
 "doctype": "Goods Details",
 "links": [],
 "property_setters": [
  {
   "_assign": null,
   "_comments": null,
   "_liked_by": null,
   "_user_tags": null,
   "creation": "2024-10-04 15:02:36.199577",
   "default_value": null,
   "doc_type": "Goods Details",
   "docstatus": 0,
   "doctype_or_field": "DocField",
   "field_name": "commodity_code",
   "idx": 0,
   "is_system_generated": 0,
   "modified": "2024-10-11 11:26:57.961046",
   "modified_by": "Administrator",
   "module": null,
   "name": "Goods Details-commodity_code-length",
   "owner": "Administrator",
   "property": "length",
   "property_type": "Int",
   "row_name": null,
   "value": "500"
  },
  {
   "_assign": null,
   "_comments": null,
   "_liked_by": null,
   "_user_tags": null,
   "creation": "2024-10-04 15:02:36.286506",
   "default_value": null,
   "doc_type": "Goods Details",
   "docstatus": 0,
   "doctype_or_field": "DocField",
   "field_name": "commodity_name",
   "idx": 0,
   "is_system_generated": 0,
   "modified": "2024-10-11 11:26:57.937338",
   "modified_by": "Administrator",
   "module": null,
   "name": "Goods Details-commodity_name-length",
   "owner": "Administrator",
   "property": "length",
   "property_type": "Int",
   "row_name": null,
   "value": "500"
  }
 ],
 "sync_on_migrate": 1
}