{
 "custom_fields": [],
 "custom_perms": [],
 "doctype": "Item",
 "links": [],
 "property_setters": [
  {
   "_assign": null,
   "_comments": null,
   "_liked_by": null,
   "_user_tags": null,
   "creation": "2024-09-04 12:37:36.550352",
   "default_value": null,
   "doc_type": "Item",
   "docstatus": 0,
   "doctype_or_field": "DocField",
   "field_name": "naming_series",
   "idx": 0,
   "is_system_generated": 0,
   "modified": "2024-10-21 11:58:46.464951",
   "modified_by": "Administrator",
   "module": null,
   "name": "Item-naming_series-options",
   "owner": "Administrator",
   "property": "options",
   "property_type": "Text",
   "row_name": null,
   "value": "STO-ITEM-.YYYY.-"
  },
  {
   "_assign": null,
   "_comments": null,
   "_liked_by": null,
   "_user_tags": null,
   "creation": "2024-06-05 08:23:28.824246",
   "default_value": null,
   "doc_type": "Item",
   "docstatus": 0,
   "doctype_or_field": "DocField",
   "field_name": "naming_series",
   "idx": 0,
   "is_system_generated": 0,
   "modified": "2024-10-21 11:58:46.455693",
   "modified_by": "Administrator",
   "module": null,
   "name": "Item-naming_series-reqd",
   "owner": "Administrator",
   "property": "reqd",
   "property_type": "Check",
   "row_name": null,
   "value": "0"
  },
  {
   "_assign": null,
   "_comments": null,
   "_liked_by": null,
   "_user_tags": null,
   "creation": "2024-06-05 08:23:29.142515",
   "default_value": null,
   "doc_type": "Item",
   "docstatus": 0,
   "doctype_or_field": "DocField",
   "field_name": "naming_series",
   "idx": 0,
   "is_system_generated": 0,
   "modified": "2024-10-21 11:58:46.403132",
   "modified_by": "Administrator",
   "module": null,
   "name": "Item-naming_series-hidden",
   "owner": "Administrator",
   "property": "hidden",
   "property_type": "Check",
   "row_name": null,
   "value": "1"
  },
  {
   "_assign": null,
   "_comments": null,
   "_liked_by": null,
   "_user_tags": null,
   "creation": "2024-06-05 08:23:29.407244",
   "default_value": null,
   "doc_type": "Item",
   "docstatus": 0,
   "doctype_or_field": "DocField",
   "field_name": "barcodes",
   "idx": 0,
   "is_system_generated": 1,
   "modified": "2024-10-21 11:58:46.376678",
   "modified_by": "Administrator",
   "module": null,
   "name": "Item-barcodes-hidden",
   "owner": "Administrator",
   "property": "hidden",
   "property_type": "Check",
   "row_name": null,
   "value": "0"
  }
 ],
 "sync_on_migrate": 1
}